{
    "menus": [
        {
            "icon": "home",
            "title": "Início",
            "url": "/clientdashboard"
        },
        {
            "icon": "person",
            "title": "Meu perfil",
            "url": "/profile"
        },
        {
            "icon": "contact_mail",
            "title": "Contato",
            "url": "/contact"
        },
        {
            "icon": "info",
            "title": "Sobre",
            "url": "/about"
        },
        {
            "icon": "logout",
            "title": "Logout",
            "url": "/"
        }
    ]
}